porta_play/PortaPlay.py
porta_play/__init__.py
porta_play/_imports_.py
porta_play/metadata.json
porta_play/package-info.json
porta_play/porta_play.min.js
porta_play/porta_play.min.js.map
porta_play-0.0.1.dist-info/LICENSE
porta_play-0.0.1.dist-info/METADATA
porta_play-0.0.1.dist-info/WHEEL
porta_play-0.0.1.dist-info/top_level.txt
porta_play-0.0.1.dist-info/RECORD
