Metadata-Version: 2.1
Name: porta-play
Version: 0.0.1
Summary: An advanced media player for plotly dash.
Home-page: UNKNOWN
Author: Nishanthan Kamaleson <n.kamaleson@portafina.co.uk>
Author-email: UNKNOWN
License: MIT
Platform: UNKNOWN
Classifier: Framework :: Dash
